setup.py
sim_reads/__init__.py
sim_reads/make_fastq.py
sim_reads.egg-info/PKG-INFO
sim_reads.egg-info/SOURCES.txt
sim_reads.egg-info/dependency_links.txt
sim_reads.egg-info/entry_points.txt
sim_reads.egg-info/requires.txt
sim_reads.egg-info/top_level.txt