Metadata-Version: 1.1
Name: sim-reads
Version: 0.0.3
Summary: Generate simulated reads.
Home-page: https://git.lumc.nl/j.f.j.laros/sim-reads
Author: LUMC, Jeroen F.J. Laros
Author-email: J.F.J.Laros@lumc.nl
License: MIT License
Keywords: bioinformatics
Platform: any
Classifier: Development Status :: 4 - Beta
Classifier: Intended Audience :: Science/Research
Classifier: Intended Audience :: Developers
Classifier: Operating System :: OS Independent
Classifier: Programming Language :: Python
Classifier: Topic :: Scientific/Engineering
